AminoExtract/__init__.py
AminoExtract/__main__.py
AminoExtract/args.py
AminoExtract/file_utils.py
AminoExtract/filter.py
AminoExtract/gff_data.py
AminoExtract/logging.py
AminoExtract/reader.py
AminoExtract/sequences.py
AminoExtract/writer.py
aminoextract-0.4.0.dist-info/METADATA
aminoextract-0.4.0.dist-info/WHEEL
aminoextract-0.4.0.dist-info/entry_points.txt
aminoextract-0.4.0.dist-info/licenses/LICENSE
aminoextract-0.4.0.dist-info/RECORD
