Metadata-Version: 2.4
Name: AminoExtract
Version: 0.4.0
Summary: Extract amino acid sequences from a fasta file based on a GFF
Project-URL: homepage, https://github.com/RIVM-bioinformatics/AminoExtract
Project-URL: source-code, https://github.com/RIVM-bioinformatics/AminoExtract
Author-email: Florian Zwagemaker <ids-bioinformatics@rivm.nl>
License-Expression: MIT
License-File: LICENSE
Classifier: Development Status :: 4 - Beta
Classifier: Intended Audience :: Science/Research
Classifier: License :: OSI Approved :: MIT License
Classifier: Operating System :: POSIX
Classifier: Programming Language :: Python :: 3.10
Classifier: Topic :: Scientific/Engineering :: Bio-Informatics
Requires-Python: >=3.10
Requires-Dist: biopython>=1.79
Requires-Dist: pandas
Requires-Dist: python-magic==0.4.*
Requires-Dist: rich==13.*
